CHANGES
LICENSE
README
flask_dogpile_cache.py
setup.py
tests.py
Flask_Dogpile_Cache.egg-info/PKG-INFO
Flask_Dogpile_Cache.egg-info/SOURCES.txt
Flask_Dogpile_Cache.egg-info/dependency_links.txt
Flask_Dogpile_Cache.egg-info/not-zip-safe
Flask_Dogpile_Cache.egg-info/requires.txt
Flask_Dogpile_Cache.egg-info/top_level.txt