Metadata-Version: 1.1
Name: Flask-Dogpile-Cache
Version: 0.2
Summary: Adds dogpile.cache support to your Flask application
Home-page: http://bitbucket.org/ponomar/flask-dogpile-cache
Author: Vitalii Ponomar
Author-email: vitalii.ponomar@gmail.com
License: BSD
Keywords: caching flask dogpile
Platform: any
Classifier: Development Status :: 4 - Beta
Classifier: Environment :: Web Environment
Classifier: Intended Audience :: Developers
Classifier: License :: OSI Approved :: BSD License
Classifier: Operating System :: OS Independent
Classifier: Programming Language :: Python
